yomigana_ebook/__init__.py
yomigana_ebook/checking.py
yomigana_ebook/cli.py
yomigana_ebook/constants.py
yomigana_ebook/converter.py
yomigana_ebook/process_ebook.py
yomigana_ebook/py.typed
yomigana_ebook/yomituki.py
yomigana_ebook-0.2.3.dist-info/LICENSE
yomigana_ebook-0.2.3.dist-info/METADATA
yomigana_ebook-0.2.3.dist-info/WHEEL
yomigana_ebook-0.2.3.dist-info/entry_points.txt
yomigana_ebook-0.2.3.dist-info/RECORD
