Metadata-Version: 2.1
Name: yomigana-ebook
Version: 0.2.3
Summary: The fastest converter to add yomigana(readings) to Japanese epub eBooks! (Using Mecab and Unidic)
Home-page: https://github.com/rabbit19981023/yomigana-ebook
License: MIT
Keywords: japanese,lightnovel,ebook,epub,furigana,yomigana,kanji,mecab,unidic,nlp
Author: Yu Chen
Author-email: rabbit19981023@gmail.com
Requires-Python: >=3.11,<4.0
Classifier: License :: OSI Approved :: MIT License
Classifier: Programming Language :: Python :: 3
Classifier: Programming Language :: Python :: 3.11
Requires-Dist: beautifulsoup4 (>=4.12.2,<5.0.0)
Requires-Dist: fugashi (>=1.2.1,<2.0.0)
Requires-Dist: lxml (>=4.9.2,<5.0.0)
Requires-Dist: unidic (>=1.1.0,<2.0.0)
Project-URL: Repository, https://github.com/rabbit19981023/yomigana-ebook
